mcp_server_vefaas_function/.python-version
mcp_server_vefaas_function/__init__.py
mcp_server_vefaas_function/main.py
mcp_server_vefaas_function/sign.py
mcp_server_vefaas_function/vefaas_server.py
mcp_server_vefaas_function/vefaas_server_test.py
mcp_server_vefaas_function-0.0.5.dist-info/METADATA
mcp_server_vefaas_function-0.0.5.dist-info/WHEEL
mcp_server_vefaas_function-0.0.5.dist-info/entry_points.txt
mcp_server_vefaas_function-0.0.5.dist-info/licenses/LICENSE
mcp_server_vefaas_function-0.0.5.dist-info/RECORD
