Metadata-Version: 2.4
Name: mcp-server-vefaas-function
Version: 0.0.5
Summary: MCP server for managing veFaaS (Volc Engine Function as a Service) functions
License-File: LICENSE
Requires-Python: >=3.12
Requires-Dist: mcp>=1.12.3
Requires-Dist: pyzipper==0.3.6
Requires-Dist: requests==2.32.3
Requires-Dist: volcengine-python-sdk>=3.0.8
